PandoraAPI/PandoraFMS_API.py
PandoraAPI/__init__.py
PandoraAPI/__main__.py
PandoraFMS_API-1.3.5.dist-info/LICENSE
PandoraFMS_API-1.3.5.dist-info/METADATA
PandoraFMS_API-1.3.5.dist-info/WHEEL
PandoraFMS_API-1.3.5.dist-info/entry_points.txt
PandoraFMS_API-1.3.5.dist-info/top_level.txt
PandoraFMS_API-1.3.5.dist-info/RECORD
