Metadata-Version: 2.1
Name: PandoraFMS-API
Version: 1.3.5
Summary: API Per extreure dades generiques dels agents de PandoraFMS
Home-page: https://github.com/NilPujolPorta/PandoraFMS_API-NPP
Author: Nil Pujol Porta
Author-email: nilpujolporta@gmail.com
License: GNU
Platform: UNKNOWN
License-File: LICENSE
Requires-Dist: argparse
Requires-Dist: setuptools (>=42)
Requires-Dist: wheel
Requires-Dist: openpyxl
Requires-Dist: pyyaml
Requires-Dist: requests
Requires-Dist: mysql-connector-python
